LICENSE
MANIFEST.in
README.md
README.rst
setup.py
docs/_build/html/errorgeopy.html
docs/_build/html/genindex.html
docs/_build/html/index.html
docs/_build/html/module.html
docs/_build/html/py-modindex.html
docs/_build/html/search.html
docs/_build/html/_modules/index.html
docs/_build/html/_modules/errorgeopy/address.html
docs/_build/html/_modules/errorgeopy/geocoders.html
docs/_build/html/_modules/errorgeopy/location.html
docs/_build/html/_modules/errorgeopy/smallestenclosingcircle.html
docs/_build/html/_modules/errorgeopy/utils.html
docs/_build/html/_static/ajax-loader.gif
docs/_build/html/_static/alabaster.css
docs/_build/html/_static/basic.css
docs/_build/html/_static/comment-bright.png
docs/_build/html/_static/comment-close.png
docs/_build/html/_static/comment.png
docs/_build/html/_static/custom.css
docs/_build/html/_static/down-pressed.png
docs/_build/html/_static/down.png
docs/_build/html/_static/file.png
docs/_build/html/_static/minus.png
docs/_build/html/_static/plus.png
docs/_build/html/_static/pygments.css
docs/_build/html/_static/up-pressed.png
docs/_build/html/_static/up.png
docs/img/delaunay-circumcircles.png
errorgeopy/__init__.py
errorgeopy/address.py
errorgeopy/geocoders.py
errorgeopy/location.py
errorgeopy/smallestenclosingcircle.py
errorgeopy/utils.py
errorgeopy.egg-info/PKG-INFO
errorgeopy.egg-info/SOURCES.txt
errorgeopy.egg-info/dependency_links.txt
errorgeopy.egg-info/requires.txt
errorgeopy.egg-info/top_level.txt