Metadata-Version: 1.1
Name: errorgeopy
Version: 1.0.1
Summary: Python geocoding in a disagreeing world
Home-page: https://github.com/alpha-beta-soup/errorgeopy
Author: Richard Law
Author-email: richard.m.law@gmail.com
License: UNKNOWN
Download-URL: https://github.com/alpha-beta-soup/errorgeopy/archive/master.zip
Platform: UNKNOWN
Classifier: Programming Language :: Python
Classifier: Programming Language :: Python :: 3 :: Only
Classifier: Development Status :: 5 - Production/Stable
Classifier: Environment :: Other Environment
Classifier: Intended Audience :: Developers
Classifier: Intended Audience :: Science/Research
Classifier: Natural Language :: English
Classifier: License :: OSI Approved :: MIT License
Classifier: Operating System :: OS Independent
Classifier: Topic :: Software Development :: Libraries :: Python Modules
Classifier: Topic :: Scientific/Engineering :: GIS
